topsis/topsis.py
Topsis_KARTIKEYA_101953023-1.0.0.dist-info/LICENSE
Topsis_KARTIKEYA_101953023-1.0.0.dist-info/METADATA
Topsis_KARTIKEYA_101953023-1.0.0.dist-info/WHEEL
Topsis_KARTIKEYA_101953023-1.0.0.dist-info/entry_points.txt
Topsis_KARTIKEYA_101953023-1.0.0.dist-info/top_level.txt
Topsis_KARTIKEYA_101953023-1.0.0.dist-info/RECORD
